{"expireTime":9007200854285261000,"key":"gatsby-plugin-mdx-entire-payload-9ec7572f2e723bb6c8f670a2f2cb9f40-","val":{"mdast":{"type":"root","children":[{"type":"jsx","value":"<Masthead title=\"Input\" subheader=\"The basis for forms\" />","position":{"start":{"line":2,"column":1,"offset":1},"end":{"line":2,"column":59,"offset":59},"indent":[]}},{"type":"heading","depth":2,"children":[{"type":"text","value":"Types","position":{"start":{"line":4,"column":4,"offset":64},"end":{"line":4,"column":9,"offset":69},"indent":[]}}],"position":{"start":{"line":4,"column":1,"offset":61},"end":{"line":4,"column":9,"offset":69},"indent":[]}},{"type":"heading","depth":3,"children":[{"type":"text","value":"Input","position":{"start":{"line":6,"column":5,"offset":75},"end":{"line":6,"column":10,"offset":80},"indent":[]}}],"position":{"start":{"line":6,"column":1,"offset":71},"end":{"line":6,"column":10,"offset":80},"indent":[]}},{"type":"paragraph","children":[{"type":"text","value":"A standard input","position":{"start":{"line":8,"column":1,"offset":82},"end":{"line":8,"column":17,"offset":98},"indent":[]}}],"position":{"start":{"line":8,"column":1,"offset":82},"end":{"line":8,"column":17,"offset":98},"indent":[]}},{"type":"code","lang":"html","meta":"live=true","value":"<div class=\"ui input\">\n    <input type=\"text\" placeholder=\"Search...\" />\n</div>","position":{"start":{"line":10,"column":1,"offset":100},"end":{"line":14,"column":4,"offset":201},"indent":[1,1,1,1]}},{"type":"heading","depth":2,"children":[{"type":"text","value":"States","position":{"start":{"line":16,"column":4,"offset":206},"end":{"line":16,"column":10,"offset":212},"indent":[]}}],"position":{"start":{"line":16,"column":1,"offset":203},"end":{"line":16,"column":10,"offset":212},"indent":[]}},{"type":"heading","depth":3,"children":[{"type":"text","value":"Focus","position":{"start":{"line":18,"column":5,"offset":218},"end":{"line":18,"column":10,"offset":223},"indent":[]}}],"position":{"start":{"line":18,"column":1,"offset":214},"end":{"line":18,"column":10,"offset":223},"indent":[]}},{"type":"paragraph","children":[{"type":"text","value":"An input field can show a user is currently interacting with it","position":{"start":{"line":19,"column":1,"offset":224},"end":{"line":19,"column":64,"offset":287},"indent":[]}}],"position":{"start":{"line":19,"column":1,"offset":224},"end":{"line":19,"column":64,"offset":287},"indent":[]}},{"type":"code","lang":"html","meta":"live=true","value":"<div class=\"ui input focus\">\n<input type=\"text\" placeholder=\"Search...\" />\n</div>","position":{"start":{"line":21,"column":1,"offset":289},"end":{"line":25,"column":4,"offset":392},"indent":[1,1,1,1]}},{"type":"heading","depth":3,"children":[{"type":"text","value":"Loading","position":{"start":{"line":27,"column":5,"offset":398},"end":{"line":27,"column":12,"offset":405},"indent":[]}}],"position":{"start":{"line":27,"column":1,"offset":394},"end":{"line":27,"column":12,"offset":405},"indent":[]}},{"type":"paragraph","children":[{"type":"text","value":"An icon input field can show that it is currently loading data","position":{"start":{"line":28,"column":1,"offset":406},"end":{"line":28,"column":63,"offset":468},"indent":[]}}],"position":{"start":{"line":28,"column":1,"offset":406},"end":{"line":28,"column":63,"offset":468},"indent":[]}},{"type":"blockquote","children":[{"type":"paragraph","children":[{"type":"text","value":"Loading inputs automatically modify the input's icon on loading state to show loading indication","position":{"start":{"line":30,"column":3,"offset":476},"end":{"line":30,"column":99,"offset":572},"indent":[]}}],"position":{"start":{"line":30,"column":3,"offset":476},"end":{"line":30,"column":99,"offset":572},"indent":[]}}],"position":{"start":{"line":30,"column":1,"offset":474},"end":{"line":30,"column":99,"offset":572},"indent":[]}},{"type":"code","lang":"html","meta":"live=true","value":"<div class=\"ui left icon input loading\">\n    <input type=\"text\" placeholder=\"Search...\" />\n    <i class=\"search icon\"></i>\n</div>","position":{"start":{"line":32,"column":1,"offset":574},"end":{"line":37,"column":4,"offset":725},"indent":[1,1,1,1,1]}},{"type":"code","lang":"html","meta":"live=true","value":"<div class=\"ui icon input loading\">\n    <input type=\"text\" placeholder=\"Search...\" />\n    <i class=\"search icon\"></i>\n</div>","position":{"start":{"line":39,"column":1,"offset":727},"end":{"line":44,"column":4,"offset":873},"indent":[1,1,1,1,1]}},{"type":"heading","depth":3,"children":[{"type":"text","value":"Disabled","position":{"start":{"line":46,"column":5,"offset":879},"end":{"line":46,"column":13,"offset":887},"indent":[]}}],"position":{"start":{"line":46,"column":1,"offset":875},"end":{"line":46,"column":13,"offset":887},"indent":[]}},{"type":"paragraph","children":[{"type":"text","value":"An input field can show that it is disabled","position":{"start":{"line":47,"column":1,"offset":888},"end":{"line":47,"column":44,"offset":931},"indent":[]}}],"position":{"start":{"line":47,"column":1,"offset":888},"end":{"line":47,"column":44,"offset":931},"indent":[]}},{"type":"code","lang":"html","meta":"live=true","value":"<div class=\"ui disabled input\">\n    <input type=\"text\" placeholder=\"Search...\" />\n</div>","position":{"start":{"line":49,"column":1,"offset":933},"end":{"line":53,"column":4,"offset":1043},"indent":[1,1,1,1]}},{"type":"code","lang":"html","meta":"live=true","value":"<div class=\"ui disabled icon input\">\n    <i class=\"search icon\"></i>\n    <input type=\"text\" placeholder=\"Search...\" />\n</div>","position":{"start":{"line":55,"column":1,"offset":1045},"end":{"line":60,"column":4,"offset":1192},"indent":[1,1,1,1,1]}},{"type":"code","lang":"html","meta":"live=true","value":"<div class=\"ui input\">\n    <input type=\"text\" placeholder=\"Search...\" disabled />\n</div>","position":{"start":{"line":62,"column":1,"offset":1194},"end":{"line":66,"column":4,"offset":1304},"indent":[1,1,1,1]}},{"type":"heading","depth":3,"children":[{"type":"text","value":"Error","position":{"start":{"line":68,"column":5,"offset":1310},"end":{"line":68,"column":10,"offset":1315},"indent":[]}}],"position":{"start":{"line":68,"column":1,"offset":1306},"end":{"line":68,"column":10,"offset":1315},"indent":[]}},{"type":"paragraph","children":[{"type":"text","value":"An input field can show the data contains errors","position":{"start":{"line":69,"column":1,"offset":1316},"end":{"line":69,"column":49,"offset":1364},"indent":[]}}],"position":{"start":{"line":69,"column":1,"offset":1316},"end":{"line":69,"column":49,"offset":1364},"indent":[]}},{"type":"code","lang":"html","meta":"live=true","value":"<div class=\"ui input error\">\n    <input type=\"text\" placeholder=\"Search...\" />\n</div>","position":{"start":{"line":71,"column":1,"offset":1366},"end":{"line":75,"column":4,"offset":1473},"indent":[1,1,1,1]}},{"type":"heading","depth":2,"children":[{"type":"text","value":"Variations","position":{"start":{"line":77,"column":4,"offset":1478},"end":{"line":77,"column":14,"offset":1488},"indent":[]}}],"position":{"start":{"line":77,"column":1,"offset":1475},"end":{"line":77,"column":14,"offset":1488},"indent":[]}},{"type":"heading","depth":3,"children":[{"type":"text","value":"Icon","position":{"start":{"line":79,"column":5,"offset":1494},"end":{"line":79,"column":9,"offset":1498},"indent":[]}}],"position":{"start":{"line":79,"column":1,"offset":1490},"end":{"line":79,"column":9,"offset":1498},"indent":[]}},{"type":"paragraph","children":[{"type":"text","value":"An input can be formatted with an icon","position":{"start":{"line":80,"column":1,"offset":1499},"end":{"line":80,"column":39,"offset":1537},"indent":[]}}],"position":{"start":{"line":80,"column":1,"offset":1499},"end":{"line":80,"column":39,"offset":1537},"indent":[]}},{"type":"blockquote","children":[{"type":"paragraph","children":[{"type":"text","value":"Input icons do not receive ","position":{"start":{"line":82,"column":3,"offset":1541},"end":{"line":82,"column":30,"offset":1568},"indent":[]}},{"type":"inlineCode","value":"pointer-events","position":{"start":{"line":82,"column":30,"offset":1568},"end":{"line":82,"column":46,"offset":1584},"indent":[]}},{"type":"text","value":" unless a ","position":{"start":{"line":82,"column":46,"offset":1584},"end":{"line":82,"column":56,"offset":1594},"indent":[]}},{"type":"inlineCode","value":"link icon","position":{"start":{"line":82,"column":56,"offset":1594},"end":{"line":82,"column":67,"offset":1605},"indent":[]}},{"type":"text","value":" is used.","position":{"start":{"line":82,"column":67,"offset":1605},"end":{"line":82,"column":76,"offset":1614},"indent":[]}}],"position":{"start":{"line":82,"column":3,"offset":1541},"end":{"line":82,"column":76,"offset":1614},"indent":[]}}],"position":{"start":{"line":82,"column":1,"offset":1539},"end":{"line":82,"column":76,"offset":1614},"indent":[]}},{"type":"code","lang":"html","meta":"live=true","value":"    <div class=\"ui icon input\">\n      <input type=\"text\" placeholder=\"Search...\" />\n      <i class=\"search icon\"></i>\n    </div>","position":{"start":{"line":84,"column":1,"offset":1616},"end":{"line":89,"column":4,"offset":1766},"indent":[1,1,1,1,1]}},{"type":"code","lang":"html","meta":"live=true","value":"<div class=\"ui left icon input\">\n    <input type=\"text\" placeholder=\"Search users...\" />\n    <i class=\"users icon\"></i>\n</div>","position":{"start":{"line":91,"column":1,"offset":1768},"end":{"line":96,"column":4,"offset":1916},"indent":[1,1,1,1,1]}},{"type":"code","lang":"html","meta":"live=true","value":"<div class=\"ui icon input\">\n    <input type=\"text\" placeholder=\"Search...\" />\n    <i class=\"circular search link icon\"></i>\n</div>","position":{"start":{"line":98,"column":1,"offset":1918},"end":{"line":103,"column":4,"offset":2070},"indent":[1,1,1,1,1]}},{"type":"code","lang":"html","meta":"live=true","value":"<div class=\"ui icon input\">\n    <input type=\"text\" placeholder=\"Search...\" />\n    <i class=\"inverted circular search link icon\"></i>\n</div>","position":{"start":{"line":105,"column":1,"offset":2072},"end":{"line":110,"column":4,"offset":2233},"indent":[1,1,1,1,1]}},{"type":"heading","depth":3,"children":[{"type":"text","value":"Labeled","position":{"start":{"line":112,"column":5,"offset":2239},"end":{"line":112,"column":12,"offset":2246},"indent":[]}}],"position":{"start":{"line":112,"column":1,"offset":2235},"end":{"line":112,"column":12,"offset":2246},"indent":[]}},{"type":"paragraph","children":[{"type":"text","value":"An input can be formatted with a label","position":{"start":{"line":113,"column":1,"offset":2247},"end":{"line":113,"column":39,"offset":2285},"indent":[]}}],"position":{"start":{"line":113,"column":1,"offset":2247},"end":{"line":113,"column":39,"offset":2285},"indent":[]}},{"type":"code","lang":"html","meta":"live=true","value":"    <div class=\"ui labeled input\">\n      <div class=\"ui label\">\n        http://\n      </div>\n      <input type=\"text\" placeholder=\"mysite.com\" />\n    </div>","position":{"start":{"line":115,"column":1,"offset":2287},"end":{"line":122,"column":4,"offset":2465},"indent":[1,1,1,1,1,1,1]}},{"type":"code","lang":"html","meta":"live=true","value":"<div class=\"ui right labeled input\">\n    <input type=\"text\" placeholder=\"Find domain\" />\n    <div class=\"ui dropdown label\">\n    <div class=\"text\">.com</div>\n    <i class=\"dropdown icon\"></i>\n    <div class=\"menu\">\n        <div class=\"item\">.com</div>\n        <div class=\"item\">.net</div>\n        <div class=\"item\">.org</div>\n    </div>\n    </div>\n</div>","position":{"start":{"line":124,"column":1,"offset":2467},"end":{"line":137,"column":4,"offset":2843},"indent":[1,1,1,1,1,1,1,1,1,1,1,1,1]}},{"type":"code","lang":"html","meta":"live=true","value":"<div class=\"ui right labeled input\">\n    <input type=\"text\" placeholder=\"Enter weight..\" />\n    <div class=\"ui basic label\">\n    kg\n    </div>\n</div>","position":{"start":{"line":139,"column":1,"offset":2845},"end":{"line":146,"column":4,"offset":3016},"indent":[1,1,1,1,1,1,1]}},{"type":"code","lang":"html","meta":"live=true","value":"<div class=\"ui right labeled input\">\n    <label for=\"amount\" class=\"ui label\">$</label>\n    <input type=\"text\" placeholder=\"Amount\" id=\"amount\" />\n    <div class=\"ui basic label\">.00</div>\n</div>","position":{"start":{"line":148,"column":1,"offset":3018},"end":{"line":154,"column":4,"offset":3235},"indent":[1,1,1,1,1,1]}},{"type":"code","lang":"html","meta":"live=true","value":"<div class=\"ui right labeled left icon input\">\n    <i class=\"tags icon\"></i>\n    <input type=\"text\" placeholder=\"Enter tags\" />\n    <a class=\"ui tag label\">\n    Add Tag\n    </a>\n</div>","position":{"start":{"line":156,"column":1,"offset":3237},"end":{"line":164,"column":4,"offset":3443},"indent":[1,1,1,1,1,1,1,1]}},{"type":"code","lang":"html","meta":"live=true","value":"<div class=\"ui left corner labeled input\">\n    <input type=\"text\" placeholder=\"Search...\" />\n    <div class=\"ui left corner label\">\n    <i class=\"asterisk icon\"></i>\n    </div>\n</div>","position":{"start":{"line":166,"column":1,"offset":3445},"end":{"line":173,"column":4,"offset":3650},"indent":[1,1,1,1,1,1,1]}},{"type":"code","lang":"html","meta":"live=true","value":"<div class=\"ui corner labeled input\">\n    <input type=\"text\" placeholder=\"Search...\" />\n    <div class=\"ui corner label\">\n    <i class=\"asterisk icon\"></i>\n    </div>\n</div>","position":{"start":{"line":175,"column":1,"offset":3652},"end":{"line":182,"column":4,"offset":3847},"indent":[1,1,1,1,1,1,1]}},{"type":"heading","depth":3,"children":[{"type":"text","value":"Action","position":{"start":{"line":184,"column":5,"offset":3853},"end":{"line":184,"column":11,"offset":3859},"indent":[]}}],"position":{"start":{"line":184,"column":1,"offset":3849},"end":{"line":184,"column":11,"offset":3859},"indent":[]}},{"type":"paragraph","children":[{"type":"text","value":"An input can be formatted to alert the user to an action they may perform","position":{"start":{"line":185,"column":1,"offset":3860},"end":{"line":185,"column":74,"offset":3933},"indent":[]}}],"position":{"start":{"line":185,"column":1,"offset":3860},"end":{"line":185,"column":74,"offset":3933},"indent":[]}},{"type":"code","lang":"html","meta":"live=true","value":"<div class=\"ui action input\">\n    <input type=\"text\" placeholder=\"Search...\" />\n    <button class=\"ui button\">Search</button>\n</div>","position":{"start":{"line":187,"column":1,"offset":3935},"end":{"line":192,"column":4,"offset":4089},"indent":[1,1,1,1,1]}},{"type":"code","lang":"html","meta":"live=true","value":"<div class=\"ui left action input\">\n    <button class=\"ui teal labeled icon button\">\n    <i class=\"cart icon\"></i>\n    Checkout\n    </button>\n    <input type=\"text\" value=\"$52.03\" />\n</div>","position":{"start":{"line":194,"column":1,"offset":4091},"end":{"line":202,"column":4,"offset":4301},"indent":[1,1,1,1,1,1,1,1]}},{"type":"code","lang":"html","meta":"live=true","value":"<div class=\"ui right action left icon input\">\n    <i class=\"search icon\"></i>\n    <input type=\"text\" placeholder=\"Search\" />\n    <div class=\"ui basic floating dropdown button\">\n    <div class=\"text\">This Page</div>\n    <i class=\"dropdown icon\"></i>\n    <div class=\"menu\">\n        <div class=\"item\">This Organization</div>\n        <div class=\"item\">Entire Site</div>\n    </div>\n    </div>\n</div>","position":{"start":{"line":204,"column":1,"offset":4303},"end":{"line":217,"column":4,"offset":4719},"indent":[1,1,1,1,1,1,1,1,1,1,1,1,1]}},{"type":"code","lang":"html","meta":"live=true","value":"<div class=\"ui action input\">\n    <input type=\"text\" placeholder=\"Search...\" />\n    <select class=\"ui compact selection dropdown\">\n    <option value=\"all\">All</option>\n    <option selected value=\"articles\">Articles</option>\n    <option value=\"products\">Products</option>\n    </select>\n    <div class=\"ui button\">Search</div>\n</div>","position":{"start":{"line":219,"column":1,"offset":4721},"end":{"line":229,"column":4,"offset":5074},"indent":[1,1,1,1,1,1,1,1,1,1]}},{"type":"code","lang":"html","meta":"live=true","value":"<div class=\"ui action input\">\n    <input type=\"text\" value=\"http://ww.short.url/c0opq\" />\n    <button class=\"ui teal right labeled icon button\">\n    <i class=\"copy icon\"></i>\n    Copy\n    </button>\n</div>","position":{"start":{"line":231,"column":1,"offset":5076},"end":{"line":239,"column":4,"offset":5302},"indent":[1,1,1,1,1,1,1,1]}},{"type":"code","lang":"html","meta":"live=true","value":"<div class=\"ui action input\">\n    <input type=\"text\" placeholder=\"Search...\" />\n    <button class=\"ui icon button\">\n    <i class=\"search icon\"></i>\n    </button>\n</div>","position":{"start":{"line":241,"column":1,"offset":5304},"end":{"line":248,"column":4,"offset":5494},"indent":[1,1,1,1,1,1,1]}},{"type":"heading","depth":3,"children":[{"type":"text","value":"Transparent","position":{"start":{"line":250,"column":5,"offset":5500},"end":{"line":250,"column":16,"offset":5511},"indent":[]}}],"position":{"start":{"line":250,"column":1,"offset":5496},"end":{"line":250,"column":16,"offset":5511},"indent":[]}},{"type":"paragraph","children":[{"type":"text","value":"A transparent input has no background","position":{"start":{"line":251,"column":1,"offset":5512},"end":{"line":251,"column":38,"offset":5549},"indent":[]}}],"position":{"start":{"line":251,"column":1,"offset":5512},"end":{"line":251,"column":38,"offset":5549},"indent":[]}},{"type":"code","lang":"html","meta":"live=true","value":"<div class=\"ui transparent input\">\n    <input type=\"text\" placeholder=\"Search...\" />\n</div>","position":{"start":{"line":253,"column":1,"offset":5551},"end":{"line":257,"column":4,"offset":5664},"indent":[1,1,1,1]}},{"type":"code","lang":"html","meta":"live=true","value":"<div class=\"ui transparent icon input\">\n    <input type=\"text\" placeholder=\"Search...\" />\n    <i class=\"search icon\"></i>\n</div>","position":{"start":{"line":259,"column":1,"offset":5666},"end":{"line":264,"column":4,"offset":5816},"indent":[1,1,1,1,1]}},{"type":"code","lang":"html","meta":"live=true","value":"<div class=\"ui transparent left icon input\">\n    <input type=\"text\" placeholder=\"Search...\" />\n    <i class=\"search icon\"></i>\n</div>","position":{"start":{"line":266,"column":1,"offset":5818},"end":{"line":271,"column":4,"offset":5973},"indent":[1,1,1,1,1]}},{"type":"heading","depth":3,"children":[{"type":"text","value":"Inverted","position":{"start":{"line":273,"column":5,"offset":5979},"end":{"line":273,"column":13,"offset":5987},"indent":[]}}],"position":{"start":{"line":273,"column":1,"offset":5975},"end":{"line":273,"column":13,"offset":5987},"indent":[]}},{"type":"paragraph","children":[{"type":"text","value":"An input can be formatted to appear on dark backgrounds","position":{"start":{"line":274,"column":1,"offset":5988},"end":{"line":274,"column":56,"offset":6043},"indent":[]}}],"position":{"start":{"line":274,"column":1,"offset":5988},"end":{"line":274,"column":56,"offset":6043},"indent":[]}},{"type":"code","lang":"html","meta":"live=true","value":"<div class=\"ui inverted segment\">\n    <div class=\"ui inverted input\">\n    <input type=\"text\" placeholder=\"Search...\" />\n    </div>\n    <div class=\"ui inverted divider\"></div>\n    <div class=\"ui inverted left icon input\">\n    <input type=\"text\" placeholder=\"Search...\" />\n    <i class=\"search icon\"></i>\n    </div>\n    <div class=\"ui inverted divider\"></div>\n    <div class=\"ui inverted transparent icon input\">\n    <input type=\"text\" placeholder=\"Search...\" />\n    <i class=\"search icon\"></i>\n    </div>\n</div>","position":{"start":{"line":276,"column":1,"offset":6045},"end":{"line":292,"column":4,"offset":6577},"indent":[1,1,1,1,1,1,1,1,1,1,1,1,1,1,1,1]}},{"type":"heading","depth":3,"children":[{"type":"text","value":"Fluid","position":{"start":{"line":295,"column":5,"offset":6584},"end":{"line":295,"column":10,"offset":6589},"indent":[]}}],"position":{"start":{"line":295,"column":1,"offset":6580},"end":{"line":295,"column":10,"offset":6589},"indent":[]}},{"type":"paragraph","children":[{"type":"text","value":"An input can take the size of its container","position":{"start":{"line":296,"column":1,"offset":6590},"end":{"line":296,"column":44,"offset":6633},"indent":[]}}],"position":{"start":{"line":296,"column":1,"offset":6590},"end":{"line":296,"column":44,"offset":6633},"indent":[]}},{"type":"code","lang":"html","meta":"live=true","value":"<div>\n    <div class=\"ui fluid icon input\">\n        <input type=\"text\" placeholder=\"Search a very wide input...\" />\n        <i class=\"search icon\"></i>\n    </div>\n    <div class=\"ui ignored divider\"></div>\n    <div class=\"ui fluid action input\">\n        <input type=\"text\" placeholder=\"Search...\" />\n        <div class=\"ui button\">Search</div>\n    </div>\n</div>","position":{"start":{"line":298,"column":1,"offset":6635},"end":{"line":310,"column":4,"offset":7018},"indent":[1,1,1,1,1,1,1,1,1,1,1,1]}},{"type":"heading","depth":3,"children":[{"type":"text","value":"Size","position":{"start":{"line":312,"column":5,"offset":7024},"end":{"line":312,"column":9,"offset":7028},"indent":[]}}],"position":{"start":{"line":312,"column":1,"offset":7020},"end":{"line":312,"column":9,"offset":7028},"indent":[]}},{"type":"paragraph","children":[{"type":"text","value":"An input can vary in size","position":{"start":{"line":313,"column":1,"offset":7029},"end":{"line":313,"column":26,"offset":7054},"indent":[]}}],"position":{"start":{"line":313,"column":1,"offset":7029},"end":{"line":313,"column":26,"offset":7054},"indent":[]}},{"type":"blockquote","children":[{"type":"paragraph","children":[{"type":"text","value":"Inputs will automatically size themselves unless you manually declare a width","position":{"start":{"line":315,"column":3,"offset":7058},"end":{"line":315,"column":80,"offset":7135},"indent":[]}}],"position":{"start":{"line":315,"column":3,"offset":7058},"end":{"line":315,"column":80,"offset":7135},"indent":[]}}],"position":{"start":{"line":315,"column":1,"offset":7056},"end":{"line":315,"column":80,"offset":7135},"indent":[]}},{"type":"code","lang":"html","meta":"live=true","value":"<div class=\"ui mini icon input\">\n    <input type=\"text\" placeholder=\"Search mini...\" />\n    <i class=\"search icon\"></i>\n</div>","position":{"start":{"line":317,"column":1,"offset":7137},"end":{"line":322,"column":4,"offset":7285},"indent":[1,1,1,1,1]}},{"type":"code","lang":"html","meta":"live=true","value":"<div class=\"ui small icon input\">\n    <input type=\"text\" placeholder=\"Search small...\" />\n    <i class=\"search icon\"></i>\n</div>","position":{"start":{"line":324,"column":1,"offset":7287},"end":{"line":329,"column":4,"offset":7437},"indent":[1,1,1,1,1]}},{"type":"code","lang":"html","meta":"live=true","value":"<div class=\"ui large icon input\">\n    <input type=\"text\" placeholder=\"Search large...\" />\n    <i class=\"search icon\"></i>\n</div>","position":{"start":{"line":331,"column":1,"offset":7439},"end":{"line":336,"column":4,"offset":7589},"indent":[1,1,1,1,1]}},{"type":"code","lang":"html","meta":"live=true","value":"<div class=\"ui big icon input\">\n    <input type=\"text\" placeholder=\"Search big...\" />\n    <i class=\"search icon\"></i>\n</div>","position":{"start":{"line":338,"column":1,"offset":7591},"end":{"line":343,"column":4,"offset":7737},"indent":[1,1,1,1,1]}},{"type":"code","lang":"html","meta":"live=true","value":"<div class=\"ui huge icon input\">\n    <input type=\"text\" placeholder=\"Search huge...\" />\n    <i class=\"search icon\"></i>\n</div>","position":{"start":{"line":345,"column":1,"offset":7739},"end":{"line":350,"column":4,"offset":7887},"indent":[1,1,1,1,1]}},{"type":"code","lang":"html","meta":"live=true","value":"<div class=\"ui massive icon input\">\n    <input type=\"text\" placeholder=\"Search massive...\" />\n    <i class=\"search icon\"></i>\n</div>","position":{"start":{"line":352,"column":1,"offset":7889},"end":{"line":357,"column":4,"offset":8043},"indent":[1,1,1,1,1]}},{"type":"export","value":"export const _frontmatter = {\"title\":\"Input\",\"path\":\"/components/input\",\"date\":\"2019-09-17T00:00:00.000Z\",\"created\":\"2019-09-17T00:00:00.000Z\"}","position":{"start":{"line":360,"column":1,"offset":8046},"end":{"line":360,"column":144,"offset":8189},"indent":[]}}],"position":{"start":{"line":1,"column":1,"offset":0},"end":{"line":360,"column":144,"offset":8189}}},"scopeImports":["import React from 'react'"],"scopeIdentifiers":["React"],"body":"function _extends() { _extends = Object.assign || function (target) { for (var i = 1; i < arguments.length; i++) { var source = arguments[i]; for (var key in source) { if (Object.prototype.hasOwnProperty.call(source, key)) { target[key] = source[key]; } } } return target; }; return _extends.apply(this, arguments); }\n\nfunction _objectWithoutProperties(source, excluded) { if (source == null) return {}; var target = _objectWithoutPropertiesLoose(source, excluded); var key, i; if (Object.getOwnPropertySymbols) { var sourceSymbolKeys = Object.getOwnPropertySymbols(source); for (i = 0; i < sourceSymbolKeys.length; i++) { key = sourceSymbolKeys[i]; if (excluded.indexOf(key) >= 0) continue; if (!Object.prototype.propertyIsEnumerable.call(source, key)) continue; target[key] = source[key]; } } return target; }\n\nfunction _objectWithoutPropertiesLoose(source, excluded) { if (source == null) return {}; var target = {}; var sourceKeys = Object.keys(source); var key, i; for (i = 0; i < sourceKeys.length; i++) { key = sourceKeys[i]; if (excluded.indexOf(key) >= 0) continue; target[key] = source[key]; } return target; }\n\n/* @jsx mdx */\nvar _frontmatter = {\n  \"title\": \"Input\",\n  \"path\": \"/components/input\",\n  \"date\": \"2019-09-17T00:00:00.000Z\",\n  \"created\": \"2019-09-17T00:00:00.000Z\"\n};\n\nvar makeShortcode = function makeShortcode(name) {\n  return function MDXDefaultShortcode(props) {\n    console.warn(\"Component \" + name + \" was not imported, exported, or provided by MDXProvider as global scope\");\n    return mdx(\"div\", props);\n  };\n};\n\nvar Masthead = makeShortcode(\"Masthead\");\nvar layoutProps = {\n  _frontmatter: _frontmatter\n};\nvar MDXLayout = \"wrapper\";\nreturn function MDXContent(_ref) {\n  var components = _ref.components,\n      props = _objectWithoutProperties(_ref, [\"components\"]);\n\n  return mdx(MDXLayout, _extends({}, layoutProps, props, {\n    components: components,\n    mdxType: \"MDXLayout\"\n  }), mdx(Masthead, {\n    title: \"Input\",\n    subheader: \"The basis for forms\",\n    mdxType: \"Masthead\"\n  }), mdx(\"h2\", null, \"Types\"), mdx(\"h3\", null, \"Input\"), mdx(\"p\", null, \"A standard input\"), mdx(\"pre\", null, mdx(\"code\", _extends({\n    parentName: \"pre\"\n  }, {\n    \"className\": \"language-html\",\n    \"metastring\": \"live=true\",\n    \"live\": \"true\"\n  }), \"<div class=\\\"ui input\\\">\\n    <input type=\\\"text\\\" placeholder=\\\"Search...\\\" />\\n</div>\\n\")), mdx(\"h2\", null, \"States\"), mdx(\"h3\", null, \"Focus\"), mdx(\"p\", null, \"An input field can show a user is currently interacting with it\"), mdx(\"pre\", null, mdx(\"code\", _extends({\n    parentName: \"pre\"\n  }, {\n    \"className\": \"language-html\",\n    \"metastring\": \"live=true\",\n    \"live\": \"true\"\n  }), \"<div class=\\\"ui input focus\\\">\\n<input type=\\\"text\\\" placeholder=\\\"Search...\\\" />\\n</div>\\n\")), mdx(\"h3\", null, \"Loading\"), mdx(\"p\", null, \"An icon input field can show that it is currently loading data\"), mdx(\"blockquote\", null, mdx(\"p\", {\n    parentName: \"blockquote\"\n  }, \"Loading inputs automatically modify the input's icon on loading state to show loading indication\")), mdx(\"pre\", null, mdx(\"code\", _extends({\n    parentName: \"pre\"\n  }, {\n    \"className\": \"language-html\",\n    \"metastring\": \"live=true\",\n    \"live\": \"true\"\n  }), \"<div class=\\\"ui left icon input loading\\\">\\n    <input type=\\\"text\\\" placeholder=\\\"Search...\\\" />\\n    <i class=\\\"search icon\\\"></i>\\n</div>\\n\")), mdx(\"pre\", null, mdx(\"code\", _extends({\n    parentName: \"pre\"\n  }, {\n    \"className\": \"language-html\",\n    \"metastring\": \"live=true\",\n    \"live\": \"true\"\n  }), \"<div class=\\\"ui icon input loading\\\">\\n    <input type=\\\"text\\\" placeholder=\\\"Search...\\\" />\\n    <i class=\\\"search icon\\\"></i>\\n</div>\\n\")), mdx(\"h3\", null, \"Disabled\"), mdx(\"p\", null, \"An input field can show that it is disabled\"), mdx(\"pre\", null, mdx(\"code\", _extends({\n    parentName: \"pre\"\n  }, {\n    \"className\": \"language-html\",\n    \"metastring\": \"live=true\",\n    \"live\": \"true\"\n  }), \"<div class=\\\"ui disabled input\\\">\\n    <input type=\\\"text\\\" placeholder=\\\"Search...\\\" />\\n</div>\\n\")), mdx(\"pre\", null, mdx(\"code\", _extends({\n    parentName: \"pre\"\n  }, {\n    \"className\": \"language-html\",\n    \"metastring\": \"live=true\",\n    \"live\": \"true\"\n  }), \"<div class=\\\"ui disabled icon input\\\">\\n    <i class=\\\"search icon\\\"></i>\\n    <input type=\\\"text\\\" placeholder=\\\"Search...\\\" />\\n</div>\\n\")), mdx(\"pre\", null, mdx(\"code\", _extends({\n    parentName: \"pre\"\n  }, {\n    \"className\": \"language-html\",\n    \"metastring\": \"live=true\",\n    \"live\": \"true\"\n  }), \"<div class=\\\"ui input\\\">\\n    <input type=\\\"text\\\" placeholder=\\\"Search...\\\" disabled />\\n</div>\\n\")), mdx(\"h3\", null, \"Error\"), mdx(\"p\", null, \"An input field can show the data contains errors\"), mdx(\"pre\", null, mdx(\"code\", _extends({\n    parentName: \"pre\"\n  }, {\n    \"className\": \"language-html\",\n    \"metastring\": \"live=true\",\n    \"live\": \"true\"\n  }), \"<div class=\\\"ui input error\\\">\\n    <input type=\\\"text\\\" placeholder=\\\"Search...\\\" />\\n</div>\\n\")), mdx(\"h2\", null, \"Variations\"), mdx(\"h3\", null, \"Icon\"), mdx(\"p\", null, \"An input can be formatted with an icon\"), mdx(\"blockquote\", null, mdx(\"p\", {\n    parentName: \"blockquote\"\n  }, \"Input icons do not receive \", mdx(\"inlineCode\", {\n    parentName: \"p\"\n  }, \"pointer-events\"), \" unless a \", mdx(\"inlineCode\", {\n    parentName: \"p\"\n  }, \"link icon\"), \" is used.\")), mdx(\"pre\", null, mdx(\"code\", _extends({\n    parentName: \"pre\"\n  }, {\n    \"className\": \"language-html\",\n    \"metastring\": \"live=true\",\n    \"live\": \"true\"\n  }), \"    <div class=\\\"ui icon input\\\">\\n      <input type=\\\"text\\\" placeholder=\\\"Search...\\\" />\\n      <i class=\\\"search icon\\\"></i>\\n    </div>\\n\")), mdx(\"pre\", null, mdx(\"code\", _extends({\n    parentName: \"pre\"\n  }, {\n    \"className\": \"language-html\",\n    \"metastring\": \"live=true\",\n    \"live\": \"true\"\n  }), \"<div class=\\\"ui left icon input\\\">\\n    <input type=\\\"text\\\" placeholder=\\\"Search users...\\\" />\\n    <i class=\\\"users icon\\\"></i>\\n</div>\\n\")), mdx(\"pre\", null, mdx(\"code\", _extends({\n    parentName: \"pre\"\n  }, {\n    \"className\": \"language-html\",\n    \"metastring\": \"live=true\",\n    \"live\": \"true\"\n  }), \"<div class=\\\"ui icon input\\\">\\n    <input type=\\\"text\\\" placeholder=\\\"Search...\\\" />\\n    <i class=\\\"circular search link icon\\\"></i>\\n</div>\\n\")), mdx(\"pre\", null, mdx(\"code\", _extends({\n    parentName: \"pre\"\n  }, {\n    \"className\": \"language-html\",\n    \"metastring\": \"live=true\",\n    \"live\": \"true\"\n  }), \"<div class=\\\"ui icon input\\\">\\n    <input type=\\\"text\\\" placeholder=\\\"Search...\\\" />\\n    <i class=\\\"inverted circular search link icon\\\"></i>\\n</div>\\n\")), mdx(\"h3\", null, \"Labeled\"), mdx(\"p\", null, \"An input can be formatted with a label\"), mdx(\"pre\", null, mdx(\"code\", _extends({\n    parentName: \"pre\"\n  }, {\n    \"className\": \"language-html\",\n    \"metastring\": \"live=true\",\n    \"live\": \"true\"\n  }), \"    <div class=\\\"ui labeled input\\\">\\n      <div class=\\\"ui label\\\">\\n        http://\\n      </div>\\n      <input type=\\\"text\\\" placeholder=\\\"mysite.com\\\" />\\n    </div>\\n\")), mdx(\"pre\", null, mdx(\"code\", _extends({\n    parentName: \"pre\"\n  }, {\n    \"className\": \"language-html\",\n    \"metastring\": \"live=true\",\n    \"live\": \"true\"\n  }), \"<div class=\\\"ui right labeled input\\\">\\n    <input type=\\\"text\\\" placeholder=\\\"Find domain\\\" />\\n    <div class=\\\"ui dropdown label\\\">\\n    <div class=\\\"text\\\">.com</div>\\n    <i class=\\\"dropdown icon\\\"></i>\\n    <div class=\\\"menu\\\">\\n        <div class=\\\"item\\\">.com</div>\\n        <div class=\\\"item\\\">.net</div>\\n        <div class=\\\"item\\\">.org</div>\\n    </div>\\n    </div>\\n</div>\\n\")), mdx(\"pre\", null, mdx(\"code\", _extends({\n    parentName: \"pre\"\n  }, {\n    \"className\": \"language-html\",\n    \"metastring\": \"live=true\",\n    \"live\": \"true\"\n  }), \"<div class=\\\"ui right labeled input\\\">\\n    <input type=\\\"text\\\" placeholder=\\\"Enter weight..\\\" />\\n    <div class=\\\"ui basic label\\\">\\n    kg\\n    </div>\\n</div>\\n\")), mdx(\"pre\", null, mdx(\"code\", _extends({\n    parentName: \"pre\"\n  }, {\n    \"className\": \"language-html\",\n    \"metastring\": \"live=true\",\n    \"live\": \"true\"\n  }), \"<div class=\\\"ui right labeled input\\\">\\n    <label for=\\\"amount\\\" class=\\\"ui label\\\">$</label>\\n    <input type=\\\"text\\\" placeholder=\\\"Amount\\\" id=\\\"amount\\\" />\\n    <div class=\\\"ui basic label\\\">.00</div>\\n</div>\\n\")), mdx(\"pre\", null, mdx(\"code\", _extends({\n    parentName: \"pre\"\n  }, {\n    \"className\": \"language-html\",\n    \"metastring\": \"live=true\",\n    \"live\": \"true\"\n  }), \"<div class=\\\"ui right labeled left icon input\\\">\\n    <i class=\\\"tags icon\\\"></i>\\n    <input type=\\\"text\\\" placeholder=\\\"Enter tags\\\" />\\n    <a class=\\\"ui tag label\\\">\\n    Add Tag\\n    </a>\\n</div>\\n\")), mdx(\"pre\", null, mdx(\"code\", _extends({\n    parentName: \"pre\"\n  }, {\n    \"className\": \"language-html\",\n    \"metastring\": \"live=true\",\n    \"live\": \"true\"\n  }), \"<div class=\\\"ui left corner labeled input\\\">\\n    <input type=\\\"text\\\" placeholder=\\\"Search...\\\" />\\n    <div class=\\\"ui left corner label\\\">\\n    <i class=\\\"asterisk icon\\\"></i>\\n    </div>\\n</div>\\n\")), mdx(\"pre\", null, mdx(\"code\", _extends({\n    parentName: \"pre\"\n  }, {\n    \"className\": \"language-html\",\n    \"metastring\": \"live=true\",\n    \"live\": \"true\"\n  }), \"<div class=\\\"ui corner labeled input\\\">\\n    <input type=\\\"text\\\" placeholder=\\\"Search...\\\" />\\n    <div class=\\\"ui corner label\\\">\\n    <i class=\\\"asterisk icon\\\"></i>\\n    </div>\\n</div>\\n\")), mdx(\"h3\", null, \"Action\"), mdx(\"p\", null, \"An input can be formatted to alert the user to an action they may perform\"), mdx(\"pre\", null, mdx(\"code\", _extends({\n    parentName: \"pre\"\n  }, {\n    \"className\": \"language-html\",\n    \"metastring\": \"live=true\",\n    \"live\": \"true\"\n  }), \"<div class=\\\"ui action input\\\">\\n    <input type=\\\"text\\\" placeholder=\\\"Search...\\\" />\\n    <button class=\\\"ui button\\\">Search</button>\\n</div>\\n\")), mdx(\"pre\", null, mdx(\"code\", _extends({\n    parentName: \"pre\"\n  }, {\n    \"className\": \"language-html\",\n    \"metastring\": \"live=true\",\n    \"live\": \"true\"\n  }), \"<div class=\\\"ui left action input\\\">\\n    <button class=\\\"ui teal labeled icon button\\\">\\n    <i class=\\\"cart icon\\\"></i>\\n    Checkout\\n    </button>\\n    <input type=\\\"text\\\" value=\\\"$52.03\\\" />\\n</div>\\n\")), mdx(\"pre\", null, mdx(\"code\", _extends({\n    parentName: \"pre\"\n  }, {\n    \"className\": \"language-html\",\n    \"metastring\": \"live=true\",\n    \"live\": \"true\"\n  }), \"<div class=\\\"ui right action left icon input\\\">\\n    <i class=\\\"search icon\\\"></i>\\n    <input type=\\\"text\\\" placeholder=\\\"Search\\\" />\\n    <div class=\\\"ui basic floating dropdown button\\\">\\n    <div class=\\\"text\\\">This Page</div>\\n    <i class=\\\"dropdown icon\\\"></i>\\n    <div class=\\\"menu\\\">\\n        <div class=\\\"item\\\">This Organization</div>\\n        <div class=\\\"item\\\">Entire Site</div>\\n    </div>\\n    </div>\\n</div>\\n\")), mdx(\"pre\", null, mdx(\"code\", _extends({\n    parentName: \"pre\"\n  }, {\n    \"className\": \"language-html\",\n    \"metastring\": \"live=true\",\n    \"live\": \"true\"\n  }), \"<div class=\\\"ui action input\\\">\\n    <input type=\\\"text\\\" placeholder=\\\"Search...\\\" />\\n    <select class=\\\"ui compact selection dropdown\\\">\\n    <option value=\\\"all\\\">All</option>\\n    <option selected value=\\\"articles\\\">Articles</option>\\n    <option value=\\\"products\\\">Products</option>\\n    </select>\\n    <div class=\\\"ui button\\\">Search</div>\\n</div>\\n\")), mdx(\"pre\", null, mdx(\"code\", _extends({\n    parentName: \"pre\"\n  }, {\n    \"className\": \"language-html\",\n    \"metastring\": \"live=true\",\n    \"live\": \"true\"\n  }), \"<div class=\\\"ui action input\\\">\\n    <input type=\\\"text\\\" value=\\\"http://ww.short.url/c0opq\\\" />\\n    <button class=\\\"ui teal right labeled icon button\\\">\\n    <i class=\\\"copy icon\\\"></i>\\n    Copy\\n    </button>\\n</div>\\n\")), mdx(\"pre\", null, mdx(\"code\", _extends({\n    parentName: \"pre\"\n  }, {\n    \"className\": \"language-html\",\n    \"metastring\": \"live=true\",\n    \"live\": \"true\"\n  }), \"<div class=\\\"ui action input\\\">\\n    <input type=\\\"text\\\" placeholder=\\\"Search...\\\" />\\n    <button class=\\\"ui icon button\\\">\\n    <i class=\\\"search icon\\\"></i>\\n    </button>\\n</div>\\n\")), mdx(\"h3\", null, \"Transparent\"), mdx(\"p\", null, \"A transparent input has no background\"), mdx(\"pre\", null, mdx(\"code\", _extends({\n    parentName: \"pre\"\n  }, {\n    \"className\": \"language-html\",\n    \"metastring\": \"live=true\",\n    \"live\": \"true\"\n  }), \"<div class=\\\"ui transparent input\\\">\\n    <input type=\\\"text\\\" placeholder=\\\"Search...\\\" />\\n</div>\\n\")), mdx(\"pre\", null, mdx(\"code\", _extends({\n    parentName: \"pre\"\n  }, {\n    \"className\": \"language-html\",\n    \"metastring\": \"live=true\",\n    \"live\": \"true\"\n  }), \"<div class=\\\"ui transparent icon input\\\">\\n    <input type=\\\"text\\\" placeholder=\\\"Search...\\\" />\\n    <i class=\\\"search icon\\\"></i>\\n</div>\\n\")), mdx(\"pre\", null, mdx(\"code\", _extends({\n    parentName: \"pre\"\n  }, {\n    \"className\": \"language-html\",\n    \"metastring\": \"live=true\",\n    \"live\": \"true\"\n  }), \"<div class=\\\"ui transparent left icon input\\\">\\n    <input type=\\\"text\\\" placeholder=\\\"Search...\\\" />\\n    <i class=\\\"search icon\\\"></i>\\n</div>\\n\")), mdx(\"h3\", null, \"Inverted\"), mdx(\"p\", null, \"An input can be formatted to appear on dark backgrounds\"), mdx(\"pre\", null, mdx(\"code\", _extends({\n    parentName: \"pre\"\n  }, {\n    \"className\": \"language-html\",\n    \"metastring\": \"live=true\",\n    \"live\": \"true\"\n  }), \"<div class=\\\"ui inverted segment\\\">\\n    <div class=\\\"ui inverted input\\\">\\n    <input type=\\\"text\\\" placeholder=\\\"Search...\\\" />\\n    </div>\\n    <div class=\\\"ui inverted divider\\\"></div>\\n    <div class=\\\"ui inverted left icon input\\\">\\n    <input type=\\\"text\\\" placeholder=\\\"Search...\\\" />\\n    <i class=\\\"search icon\\\"></i>\\n    </div>\\n    <div class=\\\"ui inverted divider\\\"></div>\\n    <div class=\\\"ui inverted transparent icon input\\\">\\n    <input type=\\\"text\\\" placeholder=\\\"Search...\\\" />\\n    <i class=\\\"search icon\\\"></i>\\n    </div>\\n</div>\\n\")), mdx(\"h3\", null, \"Fluid\"), mdx(\"p\", null, \"An input can take the size of its container\"), mdx(\"pre\", null, mdx(\"code\", _extends({\n    parentName: \"pre\"\n  }, {\n    \"className\": \"language-html\",\n    \"metastring\": \"live=true\",\n    \"live\": \"true\"\n  }), \"<div>\\n    <div class=\\\"ui fluid icon input\\\">\\n        <input type=\\\"text\\\" placeholder=\\\"Search a very wide input...\\\" />\\n        <i class=\\\"search icon\\\"></i>\\n    </div>\\n    <div class=\\\"ui ignored divider\\\"></div>\\n    <div class=\\\"ui fluid action input\\\">\\n        <input type=\\\"text\\\" placeholder=\\\"Search...\\\" />\\n        <div class=\\\"ui button\\\">Search</div>\\n    </div>\\n</div>\\n\")), mdx(\"h3\", null, \"Size\"), mdx(\"p\", null, \"An input can vary in size\"), mdx(\"blockquote\", null, mdx(\"p\", {\n    parentName: \"blockquote\"\n  }, \"Inputs will automatically size themselves unless you manually declare a width\")), mdx(\"pre\", null, mdx(\"code\", _extends({\n    parentName: \"pre\"\n  }, {\n    \"className\": \"language-html\",\n    \"metastring\": \"live=true\",\n    \"live\": \"true\"\n  }), \"<div class=\\\"ui mini icon input\\\">\\n    <input type=\\\"text\\\" placeholder=\\\"Search mini...\\\" />\\n    <i class=\\\"search icon\\\"></i>\\n</div>\\n\")), mdx(\"pre\", null, mdx(\"code\", _extends({\n    parentName: \"pre\"\n  }, {\n    \"className\": \"language-html\",\n    \"metastring\": \"live=true\",\n    \"live\": \"true\"\n  }), \"<div class=\\\"ui small icon input\\\">\\n    <input type=\\\"text\\\" placeholder=\\\"Search small...\\\" />\\n    <i class=\\\"search icon\\\"></i>\\n</div>\\n\")), mdx(\"pre\", null, mdx(\"code\", _extends({\n    parentName: \"pre\"\n  }, {\n    \"className\": \"language-html\",\n    \"metastring\": \"live=true\",\n    \"live\": \"true\"\n  }), \"<div class=\\\"ui large icon input\\\">\\n    <input type=\\\"text\\\" placeholder=\\\"Search large...\\\" />\\n    <i class=\\\"search icon\\\"></i>\\n</div>\\n\")), mdx(\"pre\", null, mdx(\"code\", _extends({\n    parentName: \"pre\"\n  }, {\n    \"className\": \"language-html\",\n    \"metastring\": \"live=true\",\n    \"live\": \"true\"\n  }), \"<div class=\\\"ui big icon input\\\">\\n    <input type=\\\"text\\\" placeholder=\\\"Search big...\\\" />\\n    <i class=\\\"search icon\\\"></i>\\n</div>\\n\")), mdx(\"pre\", null, mdx(\"code\", _extends({\n    parentName: \"pre\"\n  }, {\n    \"className\": \"language-html\",\n    \"metastring\": \"live=true\",\n    \"live\": \"true\"\n  }), \"<div class=\\\"ui huge icon input\\\">\\n    <input type=\\\"text\\\" placeholder=\\\"Search huge...\\\" />\\n    <i class=\\\"search icon\\\"></i>\\n</div>\\n\")), mdx(\"pre\", null, mdx(\"code\", _extends({\n    parentName: \"pre\"\n  }, {\n    \"className\": \"language-html\",\n    \"metastring\": \"live=true\",\n    \"live\": \"true\"\n  }), \"<div class=\\\"ui massive icon input\\\">\\n    <input type=\\\"text\\\" placeholder=\\\"Search massive...\\\" />\\n    <i class=\\\"search icon\\\"></i>\\n</div>\\n\")));\n}\n;\nMDXContent.isMDXComponent = true;","rawMDXOutput":"/* @jsx mdx */\nimport { mdx } from '@mdx-js/react';\n/* @jsx mdx */\n\nexport const _frontmatter = {\"title\":\"Input\",\"path\":\"/components/input\",\"date\":\"2019-09-17T00:00:00.000Z\",\"created\":\"2019-09-17T00:00:00.000Z\"}\nconst makeShortcode = name => function MDXDefaultShortcode(props) {\n  console.warn(\"Component \" + name + \" was not imported, exported, or provided by MDXProvider as global scope\")\n  return <div {...props}/>\n};\nconst Masthead = makeShortcode(\"Masthead\");\nconst layoutProps = {\n  _frontmatter\n};\nconst MDXLayout = \"wrapper\"\nexport default function MDXContent({\n  components,\n  ...props\n}) {\n  return <MDXLayout {...layoutProps} {...props} components={components} mdxType=\"MDXLayout\">\n    <Masthead title=\"Input\" subheader=\"The basis for forms\" mdxType=\"Masthead\" />\n    <h2>{`Types`}</h2>\n    <h3>{`Input`}</h3>\n    <p>{`A standard input`}</p>\n    <pre><code parentName=\"pre\" {...{\n        \"className\": \"language-html\",\n        \"metastring\": \"live=true\",\n        \"live\": \"true\"\n      }}>{`<div class=\"ui input\">\n    <input type=\"text\" placeholder=\"Search...\" />\n</div>\n`}</code></pre>\n    <h2>{`States`}</h2>\n    <h3>{`Focus`}</h3>\n    <p>{`An input field can show a user is currently interacting with it`}</p>\n    <pre><code parentName=\"pre\" {...{\n        \"className\": \"language-html\",\n        \"metastring\": \"live=true\",\n        \"live\": \"true\"\n      }}>{`<div class=\"ui input focus\">\n<input type=\"text\" placeholder=\"Search...\" />\n</div>\n`}</code></pre>\n    <h3>{`Loading`}</h3>\n    <p>{`An icon input field can show that it is currently loading data`}</p>\n    <blockquote>\n      <p parentName=\"blockquote\">{`Loading inputs automatically modify the input's icon on loading state to show loading indication`}</p>\n    </blockquote>\n    <pre><code parentName=\"pre\" {...{\n        \"className\": \"language-html\",\n        \"metastring\": \"live=true\",\n        \"live\": \"true\"\n      }}>{`<div class=\"ui left icon input loading\">\n    <input type=\"text\" placeholder=\"Search...\" />\n    <i class=\"search icon\"></i>\n</div>\n`}</code></pre>\n    <pre><code parentName=\"pre\" {...{\n        \"className\": \"language-html\",\n        \"metastring\": \"live=true\",\n        \"live\": \"true\"\n      }}>{`<div class=\"ui icon input loading\">\n    <input type=\"text\" placeholder=\"Search...\" />\n    <i class=\"search icon\"></i>\n</div>\n`}</code></pre>\n    <h3>{`Disabled`}</h3>\n    <p>{`An input field can show that it is disabled`}</p>\n    <pre><code parentName=\"pre\" {...{\n        \"className\": \"language-html\",\n        \"metastring\": \"live=true\",\n        \"live\": \"true\"\n      }}>{`<div class=\"ui disabled input\">\n    <input type=\"text\" placeholder=\"Search...\" />\n</div>\n`}</code></pre>\n    <pre><code parentName=\"pre\" {...{\n        \"className\": \"language-html\",\n        \"metastring\": \"live=true\",\n        \"live\": \"true\"\n      }}>{`<div class=\"ui disabled icon input\">\n    <i class=\"search icon\"></i>\n    <input type=\"text\" placeholder=\"Search...\" />\n</div>\n`}</code></pre>\n    <pre><code parentName=\"pre\" {...{\n        \"className\": \"language-html\",\n        \"metastring\": \"live=true\",\n        \"live\": \"true\"\n      }}>{`<div class=\"ui input\">\n    <input type=\"text\" placeholder=\"Search...\" disabled />\n</div>\n`}</code></pre>\n    <h3>{`Error`}</h3>\n    <p>{`An input field can show the data contains errors`}</p>\n    <pre><code parentName=\"pre\" {...{\n        \"className\": \"language-html\",\n        \"metastring\": \"live=true\",\n        \"live\": \"true\"\n      }}>{`<div class=\"ui input error\">\n    <input type=\"text\" placeholder=\"Search...\" />\n</div>\n`}</code></pre>\n    <h2>{`Variations`}</h2>\n    <h3>{`Icon`}</h3>\n    <p>{`An input can be formatted with an icon`}</p>\n    <blockquote>\n      <p parentName=\"blockquote\">{`Input icons do not receive `}<inlineCode parentName=\"p\">{`pointer-events`}</inlineCode>{` unless a `}<inlineCode parentName=\"p\">{`link icon`}</inlineCode>{` is used.`}</p>\n    </blockquote>\n    <pre><code parentName=\"pre\" {...{\n        \"className\": \"language-html\",\n        \"metastring\": \"live=true\",\n        \"live\": \"true\"\n      }}>{`    <div class=\"ui icon input\">\n      <input type=\"text\" placeholder=\"Search...\" />\n      <i class=\"search icon\"></i>\n    </div>\n`}</code></pre>\n    <pre><code parentName=\"pre\" {...{\n        \"className\": \"language-html\",\n        \"metastring\": \"live=true\",\n        \"live\": \"true\"\n      }}>{`<div class=\"ui left icon input\">\n    <input type=\"text\" placeholder=\"Search users...\" />\n    <i class=\"users icon\"></i>\n</div>\n`}</code></pre>\n    <pre><code parentName=\"pre\" {...{\n        \"className\": \"language-html\",\n        \"metastring\": \"live=true\",\n        \"live\": \"true\"\n      }}>{`<div class=\"ui icon input\">\n    <input type=\"text\" placeholder=\"Search...\" />\n    <i class=\"circular search link icon\"></i>\n</div>\n`}</code></pre>\n    <pre><code parentName=\"pre\" {...{\n        \"className\": \"language-html\",\n        \"metastring\": \"live=true\",\n        \"live\": \"true\"\n      }}>{`<div class=\"ui icon input\">\n    <input type=\"text\" placeholder=\"Search...\" />\n    <i class=\"inverted circular search link icon\"></i>\n</div>\n`}</code></pre>\n    <h3>{`Labeled`}</h3>\n    <p>{`An input can be formatted with a label`}</p>\n    <pre><code parentName=\"pre\" {...{\n        \"className\": \"language-html\",\n        \"metastring\": \"live=true\",\n        \"live\": \"true\"\n      }}>{`    <div class=\"ui labeled input\">\n      <div class=\"ui label\">\n        http://\n      </div>\n      <input type=\"text\" placeholder=\"mysite.com\" />\n    </div>\n`}</code></pre>\n    <pre><code parentName=\"pre\" {...{\n        \"className\": \"language-html\",\n        \"metastring\": \"live=true\",\n        \"live\": \"true\"\n      }}>{`<div class=\"ui right labeled input\">\n    <input type=\"text\" placeholder=\"Find domain\" />\n    <div class=\"ui dropdown label\">\n    <div class=\"text\">.com</div>\n    <i class=\"dropdown icon\"></i>\n    <div class=\"menu\">\n        <div class=\"item\">.com</div>\n        <div class=\"item\">.net</div>\n        <div class=\"item\">.org</div>\n    </div>\n    </div>\n</div>\n`}</code></pre>\n    <pre><code parentName=\"pre\" {...{\n        \"className\": \"language-html\",\n        \"metastring\": \"live=true\",\n        \"live\": \"true\"\n      }}>{`<div class=\"ui right labeled input\">\n    <input type=\"text\" placeholder=\"Enter weight..\" />\n    <div class=\"ui basic label\">\n    kg\n    </div>\n</div>\n`}</code></pre>\n    <pre><code parentName=\"pre\" {...{\n        \"className\": \"language-html\",\n        \"metastring\": \"live=true\",\n        \"live\": \"true\"\n      }}>{`<div class=\"ui right labeled input\">\n    <label for=\"amount\" class=\"ui label\">$</label>\n    <input type=\"text\" placeholder=\"Amount\" id=\"amount\" />\n    <div class=\"ui basic label\">.00</div>\n</div>\n`}</code></pre>\n    <pre><code parentName=\"pre\" {...{\n        \"className\": \"language-html\",\n        \"metastring\": \"live=true\",\n        \"live\": \"true\"\n      }}>{`<div class=\"ui right labeled left icon input\">\n    <i class=\"tags icon\"></i>\n    <input type=\"text\" placeholder=\"Enter tags\" />\n    <a class=\"ui tag label\">\n    Add Tag\n    </a>\n</div>\n`}</code></pre>\n    <pre><code parentName=\"pre\" {...{\n        \"className\": \"language-html\",\n        \"metastring\": \"live=true\",\n        \"live\": \"true\"\n      }}>{`<div class=\"ui left corner labeled input\">\n    <input type=\"text\" placeholder=\"Search...\" />\n    <div class=\"ui left corner label\">\n    <i class=\"asterisk icon\"></i>\n    </div>\n</div>\n`}</code></pre>\n    <pre><code parentName=\"pre\" {...{\n        \"className\": \"language-html\",\n        \"metastring\": \"live=true\",\n        \"live\": \"true\"\n      }}>{`<div class=\"ui corner labeled input\">\n    <input type=\"text\" placeholder=\"Search...\" />\n    <div class=\"ui corner label\">\n    <i class=\"asterisk icon\"></i>\n    </div>\n</div>\n`}</code></pre>\n    <h3>{`Action`}</h3>\n    <p>{`An input can be formatted to alert the user to an action they may perform`}</p>\n    <pre><code parentName=\"pre\" {...{\n        \"className\": \"language-html\",\n        \"metastring\": \"live=true\",\n        \"live\": \"true\"\n      }}>{`<div class=\"ui action input\">\n    <input type=\"text\" placeholder=\"Search...\" />\n    <button class=\"ui button\">Search</button>\n</div>\n`}</code></pre>\n    <pre><code parentName=\"pre\" {...{\n        \"className\": \"language-html\",\n        \"metastring\": \"live=true\",\n        \"live\": \"true\"\n      }}>{`<div class=\"ui left action input\">\n    <button class=\"ui teal labeled icon button\">\n    <i class=\"cart icon\"></i>\n    Checkout\n    </button>\n    <input type=\"text\" value=\"$52.03\" />\n</div>\n`}</code></pre>\n    <pre><code parentName=\"pre\" {...{\n        \"className\": \"language-html\",\n        \"metastring\": \"live=true\",\n        \"live\": \"true\"\n      }}>{`<div class=\"ui right action left icon input\">\n    <i class=\"search icon\"></i>\n    <input type=\"text\" placeholder=\"Search\" />\n    <div class=\"ui basic floating dropdown button\">\n    <div class=\"text\">This Page</div>\n    <i class=\"dropdown icon\"></i>\n    <div class=\"menu\">\n        <div class=\"item\">This Organization</div>\n        <div class=\"item\">Entire Site</div>\n    </div>\n    </div>\n</div>\n`}</code></pre>\n    <pre><code parentName=\"pre\" {...{\n        \"className\": \"language-html\",\n        \"metastring\": \"live=true\",\n        \"live\": \"true\"\n      }}>{`<div class=\"ui action input\">\n    <input type=\"text\" placeholder=\"Search...\" />\n    <select class=\"ui compact selection dropdown\">\n    <option value=\"all\">All</option>\n    <option selected value=\"articles\">Articles</option>\n    <option value=\"products\">Products</option>\n    </select>\n    <div class=\"ui button\">Search</div>\n</div>\n`}</code></pre>\n    <pre><code parentName=\"pre\" {...{\n        \"className\": \"language-html\",\n        \"metastring\": \"live=true\",\n        \"live\": \"true\"\n      }}>{`<div class=\"ui action input\">\n    <input type=\"text\" value=\"http://ww.short.url/c0opq\" />\n    <button class=\"ui teal right labeled icon button\">\n    <i class=\"copy icon\"></i>\n    Copy\n    </button>\n</div>\n`}</code></pre>\n    <pre><code parentName=\"pre\" {...{\n        \"className\": \"language-html\",\n        \"metastring\": \"live=true\",\n        \"live\": \"true\"\n      }}>{`<div class=\"ui action input\">\n    <input type=\"text\" placeholder=\"Search...\" />\n    <button class=\"ui icon button\">\n    <i class=\"search icon\"></i>\n    </button>\n</div>\n`}</code></pre>\n    <h3>{`Transparent`}</h3>\n    <p>{`A transparent input has no background`}</p>\n    <pre><code parentName=\"pre\" {...{\n        \"className\": \"language-html\",\n        \"metastring\": \"live=true\",\n        \"live\": \"true\"\n      }}>{`<div class=\"ui transparent input\">\n    <input type=\"text\" placeholder=\"Search...\" />\n</div>\n`}</code></pre>\n    <pre><code parentName=\"pre\" {...{\n        \"className\": \"language-html\",\n        \"metastring\": \"live=true\",\n        \"live\": \"true\"\n      }}>{`<div class=\"ui transparent icon input\">\n    <input type=\"text\" placeholder=\"Search...\" />\n    <i class=\"search icon\"></i>\n</div>\n`}</code></pre>\n    <pre><code parentName=\"pre\" {...{\n        \"className\": \"language-html\",\n        \"metastring\": \"live=true\",\n        \"live\": \"true\"\n      }}>{`<div class=\"ui transparent left icon input\">\n    <input type=\"text\" placeholder=\"Search...\" />\n    <i class=\"search icon\"></i>\n</div>\n`}</code></pre>\n    <h3>{`Inverted`}</h3>\n    <p>{`An input can be formatted to appear on dark backgrounds`}</p>\n    <pre><code parentName=\"pre\" {...{\n        \"className\": \"language-html\",\n        \"metastring\": \"live=true\",\n        \"live\": \"true\"\n      }}>{`<div class=\"ui inverted segment\">\n    <div class=\"ui inverted input\">\n    <input type=\"text\" placeholder=\"Search...\" />\n    </div>\n    <div class=\"ui inverted divider\"></div>\n    <div class=\"ui inverted left icon input\">\n    <input type=\"text\" placeholder=\"Search...\" />\n    <i class=\"search icon\"></i>\n    </div>\n    <div class=\"ui inverted divider\"></div>\n    <div class=\"ui inverted transparent icon input\">\n    <input type=\"text\" placeholder=\"Search...\" />\n    <i class=\"search icon\"></i>\n    </div>\n</div>\n`}</code></pre>\n    <h3>{`Fluid`}</h3>\n    <p>{`An input can take the size of its container`}</p>\n    <pre><code parentName=\"pre\" {...{\n        \"className\": \"language-html\",\n        \"metastring\": \"live=true\",\n        \"live\": \"true\"\n      }}>{`<div>\n    <div class=\"ui fluid icon input\">\n        <input type=\"text\" placeholder=\"Search a very wide input...\" />\n        <i class=\"search icon\"></i>\n    </div>\n    <div class=\"ui ignored divider\"></div>\n    <div class=\"ui fluid action input\">\n        <input type=\"text\" placeholder=\"Search...\" />\n        <div class=\"ui button\">Search</div>\n    </div>\n</div>\n`}</code></pre>\n    <h3>{`Size`}</h3>\n    <p>{`An input can vary in size`}</p>\n    <blockquote>\n      <p parentName=\"blockquote\">{`Inputs will automatically size themselves unless you manually declare a width`}</p>\n    </blockquote>\n    <pre><code parentName=\"pre\" {...{\n        \"className\": \"language-html\",\n        \"metastring\": \"live=true\",\n        \"live\": \"true\"\n      }}>{`<div class=\"ui mini icon input\">\n    <input type=\"text\" placeholder=\"Search mini...\" />\n    <i class=\"search icon\"></i>\n</div>\n`}</code></pre>\n    <pre><code parentName=\"pre\" {...{\n        \"className\": \"language-html\",\n        \"metastring\": \"live=true\",\n        \"live\": \"true\"\n      }}>{`<div class=\"ui small icon input\">\n    <input type=\"text\" placeholder=\"Search small...\" />\n    <i class=\"search icon\"></i>\n</div>\n`}</code></pre>\n    <pre><code parentName=\"pre\" {...{\n        \"className\": \"language-html\",\n        \"metastring\": \"live=true\",\n        \"live\": \"true\"\n      }}>{`<div class=\"ui large icon input\">\n    <input type=\"text\" placeholder=\"Search large...\" />\n    <i class=\"search icon\"></i>\n</div>\n`}</code></pre>\n    <pre><code parentName=\"pre\" {...{\n        \"className\": \"language-html\",\n        \"metastring\": \"live=true\",\n        \"live\": \"true\"\n      }}>{`<div class=\"ui big icon input\">\n    <input type=\"text\" placeholder=\"Search big...\" />\n    <i class=\"search icon\"></i>\n</div>\n`}</code></pre>\n    <pre><code parentName=\"pre\" {...{\n        \"className\": \"language-html\",\n        \"metastring\": \"live=true\",\n        \"live\": \"true\"\n      }}>{`<div class=\"ui huge icon input\">\n    <input type=\"text\" placeholder=\"Search huge...\" />\n    <i class=\"search icon\"></i>\n</div>\n`}</code></pre>\n    <pre><code parentName=\"pre\" {...{\n        \"className\": \"language-html\",\n        \"metastring\": \"live=true\",\n        \"live\": \"true\"\n      }}>{`<div class=\"ui massive icon input\">\n    <input type=\"text\" placeholder=\"Search massive...\" />\n    <i class=\"search icon\"></i>\n</div>\n`}</code></pre>\n\n    </MDXLayout>;\n}\n\n;\nMDXContent.isMDXComponent = true;"}}